dovahdf/__init__.py
dovahdf/df/__init__.py
dovahdf/df/checkpoint.py
dovahdf/df/config.py
dovahdf/df/deepfilternet.py
dovahdf/df/deepfilternet2.py
dovahdf/df/deepfilternet3.py
dovahdf/df/deepfilternetmf.py
dovahdf/df/enhance.py
dovahdf/df/evaluation_utils.py
dovahdf/df/io.py
dovahdf/df/logger.py
dovahdf/df/loss.py
dovahdf/df/lr.py
dovahdf/df/model.py
dovahdf/df/modules.py
dovahdf/df/multiframe.py
dovahdf/df/sepm.py
dovahdf/df/stoi.py
dovahdf/df/train.py
dovahdf/df/utils.py
dovahdf/df/version.py
dovahdf/df/visualization.py
dovahdf/df/scripts/dnsmos.py
dovahdf/df/scripts/dnsmos_dns5.py
dovahdf/df/scripts/dnsmos_v2.py
dovahdf/df/scripts/export.py
dovahdf/df/scripts/filter_dnsmos.py
dovahdf/df/scripts/fix_n_samples_hdf5.py
dovahdf/df/scripts/list_attrs_in_hdf5.py
dovahdf/df/scripts/model_summary.py
dovahdf/df/scripts/plot_lrs.py
dovahdf/df/scripts/plot_spec.py
dovahdf/df/scripts/plot_summaries.py
dovahdf/df/scripts/prepare_data.py
dovahdf/df/scripts/print_model.py
dovahdf/df/scripts/sample_from_hdf5.py
dovahdf/df/scripts/split_hdf5.py
dovahdf/df/scripts/test_df.py
dovahdf/df/scripts/test_dns_2020.py
dovahdf/df/scripts/test_noisy_dnsmos.py
dovahdf/df/scripts/test_voicebank_demand.py
dovahdf/df/scripts/trim_silence_hdf5.py
dovahdf/tests/__init__.py
dovahdf/tests/test_dflib.py
dovahdf-0.2.0.dist-info/METADATA
dovahdf-0.2.0.dist-info/WHEEL
dovahdf-0.2.0.dist-info/entry_points.txt
dovahdf-0.2.0.dist-info/top_level.txt
dovahdf-0.2.0.dist-info/RECORD
