Metadata-Version: 2.4
Name: dovahdf
Version: 0.2.0
Summary: Personal beta audio enhancement tool. v0.1.9: config revert+train.py update, v0.1.10: train.py bugfix, v0.1.11: train section fix, v0.1.12: new train.py error fix, v0.1.13: auto config debug, v0.1.14-16: config loading logic changes, v0.1.25: config gen+params, v0.1.26: eval logic fix, v0.2.0: matches AUDIO CLARITYv0.2!
Author-email: Dovahkiin <your.email@example.com>
License: MIT License
Classifier: Programming Language :: Python :: 3
Classifier: License :: OSI Approved :: MIT License
Classifier: Operating System :: OS Independent
Requires-Python: >=3.8
Requires-Dist: numpy<2.0,>=1.22
Requires-Dist: loguru>=0.5
Requires-Dist: appdirs>=1.4
Requires-Dist: requests>=2.27
Requires-Dist: packaging<25,>=23
Requires-Dist: sympy>=1.6
Requires-Dist: soundfile>=0.10
